<?xml version="1.0"?>
<sde:config xmlns:sde="http://www.anakeen.com/ns/sde/1.0">
    <sde:routes  namespace="AdminCenter">
        <sde:route name="AdminParameters:AllParameters">
            <sde:priority>0</sde:priority>
            <sde:callable>\Anakeen\Routes\Admin\Parameters\AllParameters</sde:callable>
            <sde:method>GET</sde:method>
            <sde:pattern>/api/v2/admin/parameters/</sde:pattern>
            <sde:description>Get all gloabl and capsule parameters</sde:description>
            <sde:requiredAccess>
                <sde:access ns="AdminCenter">Admin</sde:access>
            </sde:requiredAccess>
        </sde:route>
        <sde:route name="AdminParameters:AlterParameter">
            <sde:priority>0</sde:priority>
            <sde:callable>\Anakeen\Routes\Admin\Parameters\AlterParameter</sde:callable>
            <sde:method>PUT</sde:method>
            <sde:pattern>/api/v2/admin/parameters/{domain_name}/{parameter_name}/</sde:pattern>
            <sde:description>Modify the value of a parameter</sde:description>
            <sde:requiredAccess>
                <sde:access ns="AdminCenter">Admin</sde:access>
            </sde:requiredAccess>
        </sde:route>
    </sde:routes>
</sde:config>
